cos_python3_sdk_v5-1.3.2.dist-info/DESCRIPTION.rst
cos_python3_sdk_v5-1.3.2.dist-info/METADATA
cos_python3_sdk_v5-1.3.2.dist-info/RECORD
cos_python3_sdk_v5-1.3.2.dist-info/WHEEL
cos_python3_sdk_v5-1.3.2.dist-info/metadata.json
cos_python3_sdk_v5-1.3.2.dist-info/top_level.txt
qcloud_cos/__init__.py
qcloud_cos/cos_auth.py
qcloud_cos/cos_client.py
qcloud_cos/cos_comm.py
qcloud_cos/cos_exception.py
qcloud_cos/cos_threadpool.py
qcloud_cos/streambody.py
qcloud_cos/test.py
qcloud_cos/xml2dict.py
