Metadata-Version: 2.0
Name: cos-python3-sdk-v5
Version: 1.3.2
Summary: [UNOFFICIAL] Python 3.5 SDK for Tencent Cloud (QCloud) COS
Home-page: https://github.com/liukangxu/cos-python3-sdk-v5
Author: Kangxu Liu, tiedu, lewzylu, channingliu
Author-email: liukangxu1996@gmail.com
License: MIT
Platform: UNKNOWN
Requires-Dist: dicttoxml
Requires-Dist: requests
